padmy/__init__.py
padmy/__main__.py
padmy/anonymize/__init__.py
padmy/anonymize/anonymize.py
padmy/compare.py
padmy/config.py
padmy/db.py
padmy/env.py
padmy/logs.py
padmy/migration/__init__.py
padmy/migration/config.py
padmy/migration/create_files.py
padmy/migration/db.sql
padmy/migration/migration.py
padmy/migration/new_sql.py
padmy/migration/reorder.py
padmy/migration/run.py
padmy/migration/utils.py
padmy/run.py
padmy/sampling/__init__.py
padmy/sampling/network.py
padmy/sampling/sampling.py
padmy/sampling/viz.py
padmy/utils.py
padmy-0.25.2.dist-info/WHEEL
padmy-0.25.2.dist-info/entry_points.txt
padmy-0.25.2.dist-info/METADATA
padmy-0.25.2.dist-info/RECORD
