Metadata-Version: 2.3
Name: padmy
Version: 0.25.2
Keywords: utility
Author-email: julien.brayere@tracktor.fr
Classifier: Operating System :: OS Independent
Classifier: Programming Language :: Python :: 3
Classifier: Programming Language :: Python :: 3.12
Classifier: Programming Language :: Python :: 3.13
Classifier: Programming Language :: Python :: 3.14
Requires-Dist: piou>=0.21.0,<1.0.0
Requires-Dist: asyncpg>=0.31.0,<1.0.0
Requires-Dist: pyyaml>=6.0.2,<7.0
Requires-Dist: typing-extensions>=4.3.0 ; python_full_version < '3.11'
Requires-Dist: tracktolib>=0.42.1,<1.0.0
Requires-Dist: pytz>=2024.1,<2025.0 ; python_full_version < '3.12'
Requires-Python: >=3.12, <4.0
